pyg/__init__.py
pyg/base/__init__.py
pyg/bond/__init__.py
pyg/cells/__init__.py
pyg/encoders/__init__.py
pyg/mongo/__init__.py
pyg/npy/__init__.py
pyg/sql/__init__.py
pyg/timeseries/__init__.py
pygpyg-1.0.20230210.dist-info/METADATA
pygpyg-1.0.20230210.dist-info/WHEEL
pygpyg-1.0.20230210.dist-info/top_level.txt
pygpyg-1.0.20230210.dist-info/RECORD
