Metadata-Version: 2.1
Name: pygpyg
Version: 1.0.20230210
Summary: Utilities for data manipulation including creation of DAGs and tables
Home-page: https://github.com/gityoav/pyg
Author: Yoav Git
Author-email: yoav.git@gmail.com
Project-URL: Bug Tracker, https://github.com/gityoav/pyg/issues
Classifier: Programming Language :: Python :: 3
Classifier: License :: OSI Approved :: GNU General Public License v3 (GPLv3)
Classifier: Operating System :: OS Independent
Requires-Python: >=3.6
Requires-Dist: pyg-bond
Requires-Dist: pyg-base
Requires-Dist: pyg-encoders
Requires-Dist: pyg-sql
Requires-Dist: pyg-npy
Requires-Dist: pyg-timeseries
Requires-Dist: pyg-cell
